torch_wavelet_kan/__init__.py
torch_wavelet_kan/layer.py
torch_wavelet_kan-0.0.2.dist-info/licenses/LICENSE
torch_wavelet_kan-0.0.2.dist-info/METADATA
torch_wavelet_kan-0.0.2.dist-info/WHEEL
torch_wavelet_kan-0.0.2.dist-info/top_level.txt
torch_wavelet_kan-0.0.2.dist-info/RECORD
