Metadata-Version: 2.4
Name: torch-wavelet-kan
Version: 0.0.2
Summary: Kolmogorov-Arnold Networks using Learnable Wavelets (Morlet)
Author-email: Your Name <your.email@example.com>
License: MIT
Project-URL: Homepage, https://github.com/yourusername/torch-wavelet-kan
Classifier: Topic :: Scientific/Engineering :: Artificial Intelligence
Classifier: Programming Language :: Python :: 3
Requires-Python: >=3.8
License-File: LICENSE
Requires-Dist: torch>=2.0.0
Requires-Dist: numpy
Dynamic: license-file
